nemo_rl/__init__.py
nemo_rl/package_info.py
nemo_rl-0.0.0.dist-info/licenses/LICENSE
nemo_rl-0.0.0.dist-info/METADATA
nemo_rl-0.0.0.dist-info/WHEEL
nemo_rl-0.0.0.dist-info/top_level.txt
nemo_rl-0.0.0.dist-info/RECORD
