Metadata-Version: 2.4
Name: nemo-rl
Version: 0.0.0
Summary: NeMo RL: A Scalable and Efficient Post-Training Library for Models Ranging from 1 GPU to 1000s, and from Tiny to >100B Parameters
License: Apache 2.0
Project-URL: Homepage, https://github.com/NVIDIA/NeMo-RL
Requires-Python: >=3.10
License-File: LICENSE
Dynamic: license-file
